msmcp_template/__init__.py
msmcp_template/bin/appsettings.json
msmcp_template/bin/mcptmp
msmcp_template-0.0.12a5792017.dist-info/METADATA
msmcp_template-0.0.12a5792017.dist-info/WHEEL
msmcp_template-0.0.12a5792017.dist-info/entry_points.txt
msmcp_template-0.0.12a5792017.dist-info/licenses/LICENSE
msmcp_template-0.0.12a5792017.dist-info/licenses/NOTICE.txt
msmcp_template-0.0.12a5792017.dist-info/RECORD
