Metadata-Version: 2.4
Name: msmcp-template
Version: 0.0.12a5792017
Summary: Template MCP Server - Basic Model Context Protocol implementation
Project-URL: Homepage, https://github.com/Microsoft/mcp/blob/main/servers/Template.Mcp.Server#readme
Project-URL: Documentation, https://github.com/Microsoft/mcp/blob/main/servers/Template.Mcp.Server#readme
Project-URL: Repository, https://github.com/microsoft/mcp
Project-URL: Issues, https://github.com/microsoft/mcp/issues
Author-email: Microsoft <azuremcp@microsoft.com>
License-Expression: MIT
License-File: LICENSE
License-File: NOTICE.txt
Keywords: ai,llm,mcp,model-context-protocol,template
Classifier: Development Status :: 4 - Beta
Classifier: Environment :: Console
Classifier: Intended Audience :: Developers
Classifier: License :: OSI Approved :: MIT License
Classifier: Operating System :: POSIX :: Linux
Classifier: Programming Language :: Python :: 3
Classifier: Programming Language :: Python :: 3.10
Classifier: Programming Language :: Python :: 3.11
Classifier: Programming Language :: Python :: 3.12
Classifier: Programming Language :: Python :: 3.13
Classifier: Topic :: Software Development :: Libraries :: Python Modules
Requires-Python: >=3.10
